edutap/wallet_apple/__init__.py
edutap/wallet_apple/api.py
edutap/wallet_apple/crypto.py
edutap/wallet_apple/plugins.py
edutap/wallet_apple/protocols.py
edutap/wallet_apple/py.typed
edutap/wallet_apple/settings.py
edutap/wallet_apple/handlers/fastapi.py
edutap/wallet_apple/models/datatypes.py
edutap/wallet_apple/models/enums.py
edutap/wallet_apple/models/handlers.py
edutap/wallet_apple/models/passes.py
edutap/wallet_apple/models/semantic_tags.py
edutap/wallet_apple/models/storage.py
edutap_wallet_apple-1.0.0a2.dist-info/METADATA
edutap_wallet_apple-1.0.0a2.dist-info/WHEEL
edutap_wallet_apple-1.0.0a2.dist-info/licenses/LICENSE
edutap_wallet_apple-1.0.0a2.dist-info/RECORD
